bincrafters_remove_outdated/__init__.py
bincrafters_remove_outdated/bincrafters_remove_outdated.py
bincrafters_remove_outdated/main.py
bincrafters_remove_outdated/requirements.txt
bincrafters_remove_outdated/requirements_test.txt
bincrafters_remove_outdated-0.5.0.dist-info/LICENSE
bincrafters_remove_outdated-0.5.0.dist-info/METADATA
bincrafters_remove_outdated-0.5.0.dist-info/WHEEL
bincrafters_remove_outdated-0.5.0.dist-info/entry_points.txt
bincrafters_remove_outdated-0.5.0.dist-info/top_level.txt
bincrafters_remove_outdated-0.5.0.dist-info/RECORD
