Metadata-Version: 2.1
Name: bincrafters-remove-outdated
Version: 0.5.0
Summary: Conan script to remove all outdate packages from remote
Home-page: https://github.com/bincrafters/bincrafters-remove-outdated
Author: Bincrafters
Author-email: bincrafters@gmail.com
License: MIT
Keywords: conan,C/C++,package,libraries,developer,manager,dependency,tool,c,c++,cpp
Platform: UNKNOWN
Classifier: Development Status :: 4 - Beta
Classifier: Intended Audience :: Developers
Classifier: Topic :: Software Development :: Build Tools
Classifier: License :: OSI Approved :: MIT License
Classifier: Programming Language :: Python :: 3
Classifier: Programming Language :: Python :: 3.7
Requires-Dist: conan (>=1.7.3)
Requires-Dist: colorama (>=0.3.9)
Requires-Dist: termcolor (>=1.1.0)
Provides-Extra: test
Requires-Dist: pytest (>=3.6.2) ; extra == 'test'
Requires-Dist: pytest-cov (>=2.5.1) ; extra == 'test'
Requires-Dist: nose (<1.4.0,>=1.3.7) ; extra == 'test'
Requires-Dist: nose-parameterized (<0.6.0,>=0.5.0) ; extra == 'test'
Requires-Dist: mock (<1.4.0,>=1.3.0) ; extra == 'test'
Requires-Dist: WebTest (<2.1.0,>=2.0.18) ; extra == 'test'
